setup.cfg
setup.py
pga/__init__.py
pga.egg-info/PKG-INFO
pga.egg-info/SOURCES.txt
pga.egg-info/dependency_links.txt
pga.egg-info/not-zip-safe
pga.egg-info/requires.txt
pga.egg-info/top_level.txt