Metadata-Version: 1.0
Name: pga
Version: 0.1
Summary: This is a library for batch CV3 request and extracting data from Google Analytics into Python.
Home-page: https://github.com/Akulbasov/PGA
Author: Artem Kulbasov
Author-email: kulbasov@agima.ru
License: UNKNOWN
Platform: UNKNOWN
